Metadata-Version: 1.1
Name: waity
Version: 0.2
Summary: wait any condition
Home-page: http://github.com/ilyubin/waity
Author: Igor Lyubin
Author-email: igor.lyubin@outlook.com
License: MIT
Download-URL: https://github.com/peterldowns/mypackage/archive/0.2.tar.gz
Keywords: wait,sleep,timeout
Platform: UNKNOWN
